pragma_sdk/__init__.py
pragma_sdk/supported_assets.yaml
pragma_sdk/common/__init__.py
pragma_sdk/common/exceptions.py
pragma_sdk/common/logging.py
pragma_sdk/common/utils.py
pragma_sdk/common/configs/__init__.py
pragma_sdk/common/configs/asset_config.py
pragma_sdk/common/fetchers/__init__.py
pragma_sdk/common/fetchers/fetcher_client.py
pragma_sdk/common/fetchers/interface.py
pragma_sdk/common/fetchers/fetchers/__init__.py
pragma_sdk/common/fetchers/fetchers/binance.py
pragma_sdk/common/fetchers/fetchers/bitget.py
pragma_sdk/common/fetchers/fetchers/bitstamp.py
pragma_sdk/common/fetchers/fetchers/bybit.py
pragma_sdk/common/fetchers/fetchers/chainlink.py
pragma_sdk/common/fetchers/fetchers/coinbase.py
pragma_sdk/common/fetchers/fetchers/defillama.py
pragma_sdk/common/fetchers/fetchers/dexscreener.py
pragma_sdk/common/fetchers/fetchers/ekubo.py
pragma_sdk/common/fetchers/fetchers/erc4626.py
pragma_sdk/common/fetchers/fetchers/evm_oracle.py
pragma_sdk/common/fetchers/fetchers/gateio.py
pragma_sdk/common/fetchers/fetchers/geckoterminal.py
pragma_sdk/common/fetchers/fetchers/huobi.py
pragma_sdk/common/fetchers/fetchers/indexcoop.py
pragma_sdk/common/fetchers/fetchers/kucoin.py
pragma_sdk/common/fetchers/fetchers/lbank.py
pragma_sdk/common/fetchers/fetchers/mexc.py
pragma_sdk/common/fetchers/fetchers/okx.py
pragma_sdk/common/fetchers/fetchers/pyth.py
pragma_sdk/common/fetchers/fetchers/re7onchain.py
pragma_sdk/common/fetchers/fetchers/redstone.py
pragma_sdk/common/fetchers/fetchers/susn.py
pragma_sdk/common/fetchers/fetchers/upbit.py
pragma_sdk/common/fetchers/fetchers/usn.py
pragma_sdk/common/fetchers/future_fetchers/__init__.py
pragma_sdk/common/fetchers/future_fetchers/binance.py
pragma_sdk/common/fetchers/future_fetchers/bybit.py
pragma_sdk/common/fetchers/future_fetchers/okx.py
pragma_sdk/common/fetchers/generic_fetchers/__init__.py
pragma_sdk/common/fetchers/generic_fetchers/deribit/__init__.py
pragma_sdk/common/fetchers/generic_fetchers/deribit/fetcher.py
pragma_sdk-2.11.6.dist-info/METADATA
pragma_sdk-2.11.6.dist-info/WHEEL
pragma_sdk-2.11.6.dist-info/RECORD
