Metadata-Version: 2.4
Name: pragma-sdk
Version: 2.11.6
Summary: Core package for rollup-native Pragma Oracle
Project-URL: Homepage, https://pragma.build
Project-URL: Repository, https://github.com/Astraly-Labs/pragma-sdk
Project-URL: Documentation, https://docs.pragma.build
Author-email: 0xevolve <matthias@pragma.build>
License-Expression: MIT
Keywords: Oracle,Pragma,Starknet
Classifier: License :: OSI Approved :: MIT License
Classifier: Operating System :: OS Independent
Classifier: Programming Language :: Python :: 3
Requires-Python: <3.13,>=3.11
Requires-Dist: aioresponses>=0.7.4
Requires-Dist: deprecated>=1.2.14
Requires-Dist: grpcio-tools<1.71.0,>=1.60.0
Requires-Dist: pydantic>=2.7.4
Requires-Dist: python-dotenv>=1.0.0
Requires-Dist: pyyaml>=6.0.1
Requires-Dist: redis[hiredis]>=5.0.7
Requires-Dist: requests-mock>=1.11.0
Requires-Dist: starknet-py==0.27.0
Requires-Dist: typer==0.6.1
Requires-Dist: websockets>=14.0
Provides-Extra: dev
Requires-Dist: boto3>=1.28.61; extra == 'dev'
Requires-Dist: coverage>=7.2.1; extra == 'dev'
Requires-Dist: fakeredis[json]>=2.26.0; extra == 'dev'
Requires-Dist: moto[s3,secretsmanager]>=4.2.5; extra == 'dev'
Requires-Dist: poethepoet>=0.21.1; extra == 'dev'
Requires-Dist: pytest-asyncio>=0.21.1; extra == 'dev'
Requires-Dist: pytest-cov>=4.0.0; extra == 'dev'
Requires-Dist: pytest-mock>=3.6.1; extra == 'dev'
Requires-Dist: pytest-rerunfailures>=12.0; extra == 'dev'
Requires-Dist: pytest-xdist>=3.2.1; extra == 'dev'
Requires-Dist: pytest>=7.2.2; extra == 'dev'
Requires-Dist: ruff>=0.4; extra == 'dev'
Requires-Dist: setuptools>=68.0.0; extra == 'dev'
Provides-Extra: docs
Requires-Dist: enum-tools[sphinx]>=0.12.0; extra == 'docs'
Requires-Dist: furo>=2024.5.6; extra == 'docs'
Requires-Dist: pallets-sphinx-themes>=2.1.3; extra == 'docs'
Requires-Dist: sphinx>=7.3.7; extra == 'docs'
Provides-Extra: typing
Requires-Dist: mypy>=1.10; extra == 'typing'
Requires-Dist: types-deprecated>=1.2.9; extra == 'typing'
Requires-Dist: types-pyyaml>=6.0.12.20240311; extra == 'typing'
Requires-Dist: types-requests>=2.26.0; extra == 'typing'
